pytest_ubersmith
