Metadata-Version: 1.1
Name: pytest-ubersmith
Version: 1.0.2
Summary: Easily mock calls to ubersmith at the `requests` level.
Home-page: https://github.com/hivelocity/pytest-ubersmith
Author: Zach Kanzler
Author-email: zkanzler@hivelocity.net
License: MIT License
Platform: UNKNOWN
Classifier: Intended Audience :: Developers
Classifier: Natural Language :: English
Classifier: Operating System :: OS Independent
Classifier: Topic :: Software Development :: Testing
